pybdshadow/__init__.py
pybdshadow/analysis.py
pybdshadow/facade.py
pybdshadow/get_buildings.py
pybdshadow/preprocess.py
pybdshadow/pybdshadow.py
pybdshadow/utils.py
pybdshadow/visiblearea.py
pybdshadow/visualization.py
pybdshadow-0.3.5.dist-info/LICENSE
pybdshadow-0.3.5.dist-info/METADATA
pybdshadow-0.3.5.dist-info/WHEEL
pybdshadow-0.3.5.dist-info/top_level.txt
pybdshadow-0.3.5.dist-info/RECORD
