Metadata-Version: 2.1
Name: pybdshadow
Version: 0.3.5
Summary: Python package to generate building shadow geometry
Home-page: https://github.com/ni1o1/pybdshadow
Author: Qing Yu
Author-email: qingyu0815@foxmail.com
License: BSD
Project-URL: Bug Tracker, https://github.com/ni1o1/pybdshadow/issues
Classifier: Operating System :: OS Independent
Classifier: Topic :: Text Processing :: Indexing
Classifier: Topic :: Utilities
Classifier: Topic :: Software Development :: Libraries :: Python Modules
Classifier: License :: OSI Approved :: BSD License
Classifier: Programming Language :: Python
Classifier: Programming Language :: Python :: 3.8
Classifier: Programming Language :: Python :: 3.9
Requires-Python: >=3.8
License-File: LICENSE
Requires-Dist: numpy
Requires-Dist: pandas
Requires-Dist: shapely
Requires-Dist: geopandas
Requires-Dist: matplotlib
Requires-Dist: suncalc
Requires-Dist: keplergl
Requires-Dist: transbigdata
Requires-Dist: mapbox-vector-tile
Requires-Dist: vt2geojson
Requires-Dist: requests
Requires-Dist: tqdm
Requires-Dist: retrying
